json_to_excel_converter/__init__.py
json_to_excel_converter/cli.py
json_to_excel_converter/flatten.py
json_to_excel_converter/io_json.py
json_to_excel_converter/io_table.py
json_to_excel_converter-0.1.1.dist-info/METADATA
json_to_excel_converter-0.1.1.dist-info/WHEEL
json_to_excel_converter-0.1.1.dist-info/entry_points.txt
json_to_excel_converter-0.1.1.dist-info/licenses/LICENSE
json_to_excel_converter-0.1.1.dist-info/RECORD
