Metadata-Version: 2.4
Name: json-to-excel-converter
Version: 0.1.1
Summary: Convert large JSON to CSV/XLSX with root selection, flattening, array explode, exclusion, and header control.
Project-URL: Homepage, https://github.com/vlorenzo/json2excel-cli
Project-URL: Repository, https://github.com/vlorenzo/json2excel-cli
Project-URL: Issues, https://github.com/vlorenzo/json2excel-cli/issues
Project-URL: Documentation, https://github.com/vlorenzo/json2excel-cli#readme
Author-email: Lorenzo Verna <v.lorenzo@gmail.com>
License: MIT
License-File: LICENSE
Keywords: cli,csv,data-conversion,excel,json,xlsx
Classifier: Development Status :: 4 - Beta
Classifier: Environment :: Console
Classifier: Intended Audience :: Developers
Classifier: Intended Audience :: End Users/Desktop
Classifier: License :: OSI Approved :: MIT License
Classifier: Operating System :: OS Independent
Classifier: Programming Language :: Python :: 3
Classifier: Programming Language :: Python :: 3.12
Classifier: Topic :: Office/Business :: Financial :: Spreadsheet
Classifier: Topic :: Text Processing :: Markup
Classifier: Topic :: Utilities
Requires-Python: >=3.12
Requires-Dist: ijson>=3.4.0
Requires-Dist: openpyxl>=3.1.5
Requires-Dist: orjson>=3.11.3
Requires-Dist: rich>=14.1.0
Requires-Dist: typer>=0.19.2
